[
    { "id": 1, "branch_name": "Điện thoại", "industry_id": 1, "active": "TRUE" },
    { "id": 2, "branch_name": "Máy tính bảng", "industry_id": 1, "active": "TRUE" },
    { "id": 3, "branch_name": "Laptop", "industry_id": 2, "active": "TRUE" },
    { "id": 4, "branch_name": "Chuột", "industry_id": 2, "active": "TRUE" },
    { "id": 5, "branch_name": "Bàn phím", "industry_id": 2, "active": "TRUE" },
    { "id": 6, "branch_name": "USB", "industry_id": 2, "active": "TRUE" },
    { "id": 7, "branch_name": "Tivi thông minh", "industry_id": 3, "active": "TRUE" },
    { "id": 8, "branch_name": "Tivi thường", "industry_id": 3, "active": "TRUE" },
    { "id": 9, "branch_name": "Máy ảnh", "industry_id": 4, "active": "TRUE" },
    { "id": 10, "branch_name": "Ống kính - Lens", "industry_id": 4, "active": "TRUE" },
    { "id": 11, "branch_name": "Camera bảo vệ", "industry_id": 4, "active": "TRUE" },
    { "id": 12, "branch_name": "Thực phẩm", "industry_id": 5, "active": "TRUE" },
    { "id": 13, "branch_name": "Đồ uống - giải khát", "industry_id": 5, "active": "TRUE" },
    { "id": 14, "branch_name": "Bánh kẹo", "industry_id": 5, "active": "TRUE" },
    { "id": 15, "branch_name": "Thể thao", "industry_id": 6, "active": "TRUE" },
    { "id": 16, "branch_name": "Dã ngoại", "industry_id": 6, "active": "TRUE" },
    { "id": 17, "branch_name": "GYM", "industry_id": 6, "active": "TRUE" },
    { "id": 18, "branch_name": "Nhà tắm", "industry_id": 7, "active": "TRUE" },
    { "id": 19, "branch_name": "Nhà bếp", "industry_id": 7, "active": "TRUE" },
    { "id": 20, "branch_name": "Phòng ngủ", "industry_id": 7, "active": "TRUE" },
    { "id": 21, "branch_name": "Đồ chơi", "industry_id": 8, "active": "TRUE" },
    { "id": 22, "branch_name": "Đồ dùng cho mẹ", "industry_id": 8, "active": "TRUE" },
    { "id": 23, "branch_name": "Đồ dùng cho bé", "industry_id": 8, "active": "TRUE" },
    { "id": 24, "branch_name": "Xe máy", "industry_id": 9, "active": "TRUE" },
    { "id": 25, "branch_name": "Ô tô", "industry_id": 9, "active": "TRUE" },
    { "id": 26, "branch_name": "Xe đạp", "industry_id": 9, "active": "TRUE" },
    { "id": 27, "branch_name": "Văn học Việt Nam", "industry_id": 10, "active": "TRUE" },
    { "id": 28, "branch_name": "Văn học nước ngoài", "industry_id": 10, "active": "TRUE" }
]
